fossology/__init__.py
fossology/api.py
fossology/exceptions.py
fossology/resources.py
fossology/utils.py
py_fossology-0.1.1.dist-info/LICENSE
py_fossology-0.1.1.dist-info/METADATA
py_fossology-0.1.1.dist-info/WHEEL
py_fossology-0.1.1.dist-info/top_level.txt
py_fossology-0.1.1.dist-info/RECORD
