Metadata-Version: 2.1
Name: py-fossology
Version: 0.1.1
Summary: Python wrapper around FOSSology's REST API
Home-page: https://github.com/kalsi-avneet/py-fossology
Author: Avneet Singh
License: UNKNOWN
Platform: UNKNOWN
Requires-Python: >=3.5
Requires-Dist: requests (==2.22.0)
